pyrf24/__init__.py
pyrf24/fake_ble.py
pyrf24/py.typed
pyrf24/pyrf24.cpython-314t-x86_64-linux-gnu.so
pyrf24/pyrf24.pyi
pyrf24-0.6.0.dist-info/METADATA
pyrf24-0.6.0.dist-info/WHEEL
pyrf24-0.6.0.dist-info/top_level.txt
pyrf24-0.6.0.dist-info/RECORD
pyrf24-0.6.0.dist-info/licenses/LICENSE
