Metadata-Version: 2.4
Name: pyrf24
Version: 0.6.0
Summary: A python package wrapping the nRF24 C++ libraries.
Author-email: Brendan Doherty <2bndy5@gmail.com>
License-Expression: GPL-2.0-only
Project-URL: Documentation, http://nRF24.github.io/pyRF24
Project-URL: Source, https://github.com/nRF24/pyRF24
Project-URL: Tracker, https://github.com/nRF24/pyRF24/issues
Keywords: nrf24l01,nRF24L01+,raspberry,pi,driver,radio,transceiver,RF24,RF24Network,RF24Mesh
Classifier: Development Status :: 5 - Production/Stable
Classifier: Intended Audience :: Developers
Classifier: Operating System :: POSIX :: Linux
Classifier: Programming Language :: C++
Classifier: Programming Language :: Python :: 3
Classifier: Topic :: Software Development :: Libraries
Classifier: Topic :: System :: Hardware
Classifier: Topic :: System :: Hardware :: Hardware Drivers
Classifier: Topic :: System :: Networking
Classifier: Typing :: Typed
Requires-Python: >=3.9
License-File: LICENSE
Requires-Dist: typing-extensions; python_version < "3.13"
Dynamic: license-file
